sentry_dingtalk_ihoey/__init__.py
sentry_dingtalk_ihoey/forms.py
sentry_dingtalk_ihoey/plugin.py
sentry_dingtalk_ihoey-1.0.7.dist-info/LICENSE
sentry_dingtalk_ihoey-1.0.7.dist-info/METADATA
sentry_dingtalk_ihoey-1.0.7.dist-info/WHEEL
sentry_dingtalk_ihoey-1.0.7.dist-info/entry_points.txt
sentry_dingtalk_ihoey-1.0.7.dist-info/top_level.txt
sentry_dingtalk_ihoey-1.0.7.dist-info/RECORD
