Metadata-Version: 2.1
Name: sentry-dingtalk-ihoey
Version: 1.0.7
Summary: sentry extension which can send error to dingtalk.
Home-page: https://github.com/ihoey/sentry_dingtalk_ihoey
Author: ihoey
Author-email: mail@ihoey.com
License: MIT
Keywords: sentry dingtalk dingding ihoey
Platform: UNKNOWN
Classifier: Framework :: Django
Classifier: Intended Audience :: Developers
Classifier: Operating System :: OS Independent
Classifier: Natural Language :: Chinese (Simplified)
Classifier: Programming Language :: Python :: 2.7
Classifier: License :: OSI Approved :: MIT License
Requires-Dist: sentry
Requires-Dist: requests
Requires-Dist: Django
